setup.cfg
setup.py
exceldraw/__init__.py
exceldraw/d2.py
exceldraw/drawex.py
exceldraw.egg-info/PKG-INFO
exceldraw.egg-info/SOURCES.txt
exceldraw.egg-info/dependency_links.txt
exceldraw.egg-info/not-zip-safe
exceldraw.egg-info/top_level.txt