Metadata-Version: 1.0
Name: exceldraw
Version: 1.1
Summary: Draw your Excel image
Home-page: UNKNOWN
Author: UNKNOWN
Author-email: ujjayanta.bhaumik.18@ucl.ac.uk
License: UNKNOWN
Platform: UNKNOWN
